lm_global_fit/__init__.py
lm_global_fit/global_fit.py
lm_global_fit-1.0.1.dist-info/licenses/LICENSE
lm_global_fit-1.0.1.dist-info/METADATA
lm_global_fit-1.0.1.dist-info/WHEEL
lm_global_fit-1.0.1.dist-info/top_level.txt
lm_global_fit-1.0.1.dist-info/RECORD
